.gitignore
LICENSE
README.md
logo.png
setup.py
docs/index.html
docs/pynkowski.html
docs/search.js
docs/pynkowski/__version.html
docs/pynkowski/data.html
docs/pynkowski/stats.html
docs/pynkowski/theory.html
docs/pynkowski/data/array.html
docs/pynkowski/data/base_da.html
docs/pynkowski/data/healpix.html
docs/pynkowski/data/so3data.html
docs/pynkowski/data/utils_da.html
docs/pynkowski/stats/extrema.html
docs/pynkowski/stats/minkowski.html
docs/pynkowski/stats/utils_st.html
docs/pynkowski/theory/base_th.html
docs/pynkowski/theory/chi2.html
docs/pynkowski/theory/gaussian.html
docs/pynkowski/theory/spingaussian.html
docs/pynkowski/theory/utils_th.html
examples/P2.ipynb
examples/Temperature.ipynb
pynkowski/__init__.py
pynkowski/__version.py
pynkowski.egg-info/PKG-INFO
pynkowski.egg-info/SOURCES.txt
pynkowski.egg-info/dependency_links.txt
pynkowski.egg-info/requires.txt
pynkowski.egg-info/top_level.txt
pynkowski/data/__init__.py
pynkowski/data/array.py
pynkowski/data/base_da.py
pynkowski/data/healpix.py
pynkowski/data/so3data.py
pynkowski/data/utils_da.py
pynkowski/stats/__init__.py
pynkowski/stats/extrema.py
pynkowski/stats/minkowski.py
pynkowski/stats/utils_st.py
pynkowski/theory/__init__.py
pynkowski/theory/base_th.py
pynkowski/theory/chi2.py
pynkowski/theory/gaussian.py
pynkowski/theory/spingaussian.py
pynkowski/theory/utils_th.py